napari_flim_phasor_plotter/__init__.py
napari_flim_phasor_plotter/_calibration.py
napari_flim_phasor_plotter/_plotting.py
napari_flim_phasor_plotter/_reader.py
napari_flim_phasor_plotter/_synthetic.py
napari_flim_phasor_plotter/filters.py
napari_flim_phasor_plotter/napari.yaml
napari_flim_phasor_plotter/phasors.py
napari_flim_phasor_plotter/sample_data.py
napari_flim_phasor_plotter/widgets.py
napari_flim_phasor_plotter/_tests/__init__.py
napari_flim_phasor_plotter/_tests/test_convert_to_ome_tif.py
napari_flim_phasor_plotter/_tests/test_convert_to_zarr.py
napari_flim_phasor_plotter/_tests/test_filters.py
napari_flim_phasor_plotter/_tests/test_reader.py
napari_flim_phasor_plotter/_tests/test_sample_data.py
napari_flim_phasor_plotter/_tests/test_widget.py
napari_flim_phasor_plotter/convert/__init__.py
napari_flim_phasor_plotter/convert/_utilities.py
napari_flim_phasor_plotter/convert/convert_to_ome_tif.py
napari_flim_phasor_plotter/convert/convert_to_zarr.py
napari_flim_phasor_plotter/data/hazelnut_FLIM_single_image.ptu
napari_flim_phasor_plotter/data/lifetime_cat.tif
napari_flim_phasor_plotter/data/lifetime_cat_labels.tif
napari_flim_phasor_plotter/data/lifetime_cat_metadata.yml
napari_flim_phasor_plotter/data/seminal_receptacle_FLIM_single_image.sdt
napari_flim_phasor_plotter-0.2.2.dist-info/licenses/LICENSE
napari_flim_phasor_plotter-0.2.2.dist-info/METADATA
napari_flim_phasor_plotter-0.2.2.dist-info/WHEEL
napari_flim_phasor_plotter-0.2.2.dist-info/entry_points.txt
napari_flim_phasor_plotter-0.2.2.dist-info/top_level.txt
napari_flim_phasor_plotter-0.2.2.dist-info/RECORD
