Metadata-Version: 2.4
Name: napari-flim-phasor-plotter
Version: 0.2.2
Summary: A plugin that performs phasor plot from TCSPC FLIM data.
Home-page: https://github.com/zoccoler/napari-flim-phasor-plotter
Author: Marcelo L. Zoccoler, Cornelia Wetzker
Author-email: marzoccoler@gmail.com
License: BSD-3-Clause
Project-URL: Bug Tracker, https://github.com/zoccoler/napari-flim-phasor-plotter/issues
Project-URL: Documentation, https://github.com/zoccoler/napari-flim-phasor-plotter#README.md
Project-URL: Source Code, https://github.com/zoccoler/napari-flim-phasor-plotter
Project-URL: User Support, https://github.com/zoccoler/napari-flim-phasor-plotter/issues
Classifier: Development Status :: 2 - Pre-Alpha
Classifier: Framework :: napari
Classifier: Intended Audience :: Developers
Classifier: License :: OSI Approved :: BSD License
Classifier: Operating System :: OS Independent
Classifier: Programming Language :: Python
Classifier: Programming Language :: Python :: 3
Classifier: Programming Language :: Python :: 3 :: Only
Classifier: Programming Language :: Python :: 3.9
Classifier: Programming Language :: Python :: 3.10
Classifier: Programming Language :: Python :: 3.11
Classifier: Topic :: Scientific/Engineering :: Visualization
Classifier: Topic :: Scientific/Engineering :: Image Processing
Requires-Python: >=3.9
License-File: LICENSE
Requires-Dist: numpy
Requires-Dist: magicgui
Requires-Dist: qtpy
Requires-Dist: napari>=0.4.19
Requires-Dist: napari-clusters-plotter<0.9.0,>=0.8.1
Requires-Dist: ptufile
Requires-Dist: sdtfile
Requires-Dist: natsort
Requires-Dist: rocket-fft
Requires-Dist: dask
Requires-Dist: zarr
Requires-Dist: napari-segment-blobs-and-things-with-membranes
Requires-Dist: napari-skimage-regionprops
Requires-Dist: scikit-image>=0.20.0
Provides-Extra: testing
Requires-Dist: tox; extra == "testing"
Requires-Dist: pytest; extra == "testing"
Requires-Dist: pytest-cov; extra == "testing"
Requires-Dist: pytest-qt; extra == "testing"
Requires-Dist: napari; extra == "testing"
Requires-Dist: pyqt5; extra == "testing"
Dynamic: license-file
